odfdo/.DS_Store
odfdo/__init__.py
odfdo/annotation.py
odfdo/body.py
odfdo/bookmark.py
odfdo/cell.py
odfdo/column.py
odfdo/config_elements.py
odfdo/const.py
odfdo/container.py
odfdo/content.py
odfdo/datatype.py
odfdo/document.py
odfdo/draw_page.py
odfdo/element.py
odfdo/element_strip.py
odfdo/element_typed.py
odfdo/elements_between.py
odfdo/form.py
odfdo/form_controls.py
odfdo/form_controls_mixins.py
odfdo/form_properties.py
odfdo/frame.py
odfdo/header.py
odfdo/header_rows.py
odfdo/image.py
odfdo/line_break.py
odfdo/link.py
odfdo/list.py
odfdo/manifest.py
odfdo/master_page.py
odfdo/meta.py
odfdo/meta_auto_reload.py
odfdo/meta_field.py
odfdo/meta_hyperlink_behaviour.py
odfdo/meta_template.py
odfdo/meta_user_defined.py
odfdo/mixin_dc_creator.py
odfdo/mixin_dc_date.py
odfdo/mixin_link.py
odfdo/mixin_list.py
odfdo/mixin_md.py
odfdo/mixin_named_range.py
odfdo/mixin_paragraph.py
odfdo/mixin_paragraph_formatted.py
odfdo/mixin_toc.py
odfdo/named_range.py
odfdo/note.py
odfdo/office_forms.py
odfdo/page_layout.py
odfdo/paragraph.py
odfdo/presentation_notes.py
odfdo/py.typed
odfdo/reference.py
odfdo/row.py
odfdo/row_group.py
odfdo/ruby_base.py
odfdo/scripts/__init__.py
odfdo/scripts/diff.py
odfdo/scripts/folder.py
odfdo/scripts/from_csv.py
odfdo/scripts/headers.py
odfdo/scripts/highlight.py
odfdo/scripts/meta_print.py
odfdo/scripts/meta_update.py
odfdo/scripts/replace.py
odfdo/scripts/show.py
odfdo/scripts/styles.py
odfdo/scripts/table_shrink.py
odfdo/scripts/to_csv.py
odfdo/scripts/to_markdown.py
odfdo/scripts/userfield.py
odfdo/section.py
odfdo/settings.py
odfdo/shapes.py
odfdo/smil.py
odfdo/spacer.py
odfdo/span.py
odfdo/style.py
odfdo/style_base.py
odfdo/style_containers.py
odfdo/style_defaults.py
odfdo/style_props.py
odfdo/style_utils.py
odfdo/styles.py
odfdo/svg.py
odfdo/tab.py
odfdo/table.py
odfdo/table_cache.py
odfdo/templates/__init__.py
odfdo/templates/drawing.otg
odfdo/templates/lpod_styles.odt
odfdo/templates/presentation.otp
odfdo/templates/spreadsheet.ots
odfdo-3.20.0.dist-info/WHEEL
odfdo-3.20.0.dist-info/entry_points.txt
odfdo-3.20.0.dist-info/METADATA
odfdo-3.20.0.dist-info/RECORD
