Metadata-Version: 2.4
Name: odfdo
Version: 3.20.0
Summary: Python library for OpenDocument Format
Keywords: python,library,ODF,OpenDocument
Author: Jérôme Dumonteil
Author-email: Jérôme Dumonteil <jerome.dumonteil@gmail.com>
License-Expression: Apache-2.0
Classifier: Development Status :: 5 - Production/Stable
Classifier: Environment :: Console
Classifier: Intended Audience :: Developers
Classifier: License :: OSI Approved :: Apache Software License
Classifier: Programming Language :: Python
Classifier: Programming Language :: Python :: 3
Classifier: Programming Language :: Python :: 3 :: Only
Classifier: Programming Language :: Python :: 3.9
Classifier: Programming Language :: Python :: 3.10
Classifier: Programming Language :: Python :: 3.11
Classifier: Programming Language :: Python :: 3.12
Classifier: Programming Language :: Python :: 3.13
Classifier: Programming Language :: Python :: 3.14
Classifier: Operating System :: OS Independent
Classifier: Topic :: Software Development :: Libraries :: Python Modules
Requires-Dist: lxml>=4.8.0,<5 ; python_full_version == '3.9.*'
Requires-Dist: lxml>=4.8.0,<5.1.1 ; python_full_version == '3.10.*'
Requires-Dist: lxml>=4.9.4,<7 ; python_full_version >= '3.11' and python_full_version < '3.13'
Requires-Dist: lxml>=5.3.0,<7 ; python_full_version >= '3.13'
Requires-Python: >=3.9, <4
Project-URL: changelog, https://github.com/jdum/odfdo/blob/main/CHANGES.md
Project-URL: documentation, https://jdum.github.io/odfdo/
Project-URL: homepage, https://github.com/jdum/odfdo
Project-URL: repository, https://github.com/jdum/odfdo
